IPcalculation/IPcalculation.py
IPcalculation/__init__.py
IPcalculation-1.0.7.dist-info/LICENSE
IPcalculation-1.0.7.dist-info/METADATA
IPcalculation-1.0.7.dist-info/WHEEL
IPcalculation-1.0.7.dist-info/top_level.txt
IPcalculation-1.0.7.dist-info/RECORD
