Metadata-Version: 2.1
Name: IPcalculation
Version: 1.0.7
Summary: Pacote para calculos matematicos
Home-page: https://github.com/PauloHenrique-UFPI/POO-FINAL.git
Author: Paulo Henrique, Isdael Oliveira
Author-email: hunter404paulo@gmail.com, isdael.oliveira@gmail.com
License: UNKNOWN
Project-URL: Bug Tracker, https://github.com/pypa/sampleproject/issues
Platform: UNKNOWN
Classifier: Programming Language :: Python :: 3
Classifier: License :: OSI Approved :: MIT License
Classifier: Operating System :: OS Independent
Requires-Python: >=3.6
License-File: LICENSE
